MANIFEST.in
README.rst
setup.cfg
setup.py
sen14348_exporter/__about__.py
sen14348_exporter/__init__.py
sen14348_exporter/__main__.py
sen14348_exporter/exporter.py
sen14348_exporter.egg-info/PKG-INFO
sen14348_exporter.egg-info/SOURCES.txt
sen14348_exporter.egg-info/dependency_links.txt
sen14348_exporter.egg-info/entry_points.txt
sen14348_exporter.egg-info/requires.txt
sen14348_exporter.egg-info/top_level.txt