Metadata-Version: 1.1
Name: sen14348-exporter
Version: 0.1.0
Summary: Prometheus exporter for the SparkFun SEN-14348 Environmental Combo Breakout
Home-page: https://github.com/ashtreefarms/sen14348_exporter
Author: Jake Krog
Author-email: jake.krog@gmail.com
License: MIT
Keywords: sparkfun,raspberry pi,rpi,prometheus,BME280,CCS811,i2c,temperature,humidity,pressure,eco2,tvoc
Platform: UNKNOWN
Classifier: Development Status :: 4 - Beta
Classifier: Environment :: Console
Classifier: Intended Audience :: Education
Classifier: Intended Audience :: Developers
Classifier: License :: OSI Approved :: MIT License
Classifier: Programming Language :: Python :: 3
Classifier: Topic :: System :: Monitoring
